Workbook

Sheet Costo de capital
A1: Costo de capital de SweetKids México: CAPM y costo promedio ponderado (WACC)
A3: Componente | B3: Valor | C3: Comentario
A4: Tasa libre de riesgo (bono del Tesoro de EE. UU. a 10 años) | B4: 0.043 | C4: Supuesto en dólares
A5: Prima de riesgo país México | B5: 0.025 | C5: Supuesto
A6: Beta del sector alimentos | B6: 1 | C6: Supuesto: sector de consumo básico
A7: Prima de riesgo de mercado | B7: 0.055 | C7: Supuesto
A8: Costo del capital propio (Ke) = rf + riesgo país + beta × prima | B8: =B4+B5+B6*B7 -> 0.123 | C8: Modelo CAPM
A9: Costo de la deuda bancaria antes de impuestos (Kd) | B9: 0.1 | C9: Supuesto: crédito de la expansión de 2022
A10: Tasa de ISR en México | B10: 0.3 | C10: Tasa corporativa
A11: Costo de la deuda después de impuestos | B11: =B9*(1-B10) -> 0.07 | C11: Kd × (1 − ISR)
A12: Peso de la deuda (D / V) | B12: 0.25 | C12: Deuda de USD 15 M sobre un valor cercano a USD 60 M
A13: Peso del capital (E / V) | B13: =1-B12 -> 0.75
A14: Costo de capital promedio ponderado (WACC) | B14: =B13*B8+B12*B11 -> 0.10975 | C14: Tasa de descuento del flujo de caja libre
A16: Cifras en azul = supuestos; en negro = fórmulas. Escenario hipotético con fines académicos.

Sheet Múltiplos (preliminar)
A1: Momento 1. Estimación preliminar antes de la auditoría (millones de USD)
A3: Concepto | B3: Valor | C3: Comentario
A4: Ventas 2025 | B4: 50 | C4: Supuesto: el caso no informa las ventas
A5: EBITDA 2025 | B5: 7.5 | C5: Supuesto: margen de 15%, calibrado para llegar a los USD 60 M del caso
A6: Margen EBITDA | B6: =B5/B4 -> 0.15
A7: Múltiplo VE / EBITDA de empresas comparables | B7: 8 | C7: Golosinas y snacks saludables
A8: Valor estimado de SweetKids (antes de auditoría) | B8: =B5*B7 -> 60 | C8: Supone una empresa sin deuda
A10: Coincide con la estimación del caso: USD 60 millones.

Sheet Flujo de caja libre (DCF)
A1: Momento 2. Valoración formal posterior a la due diligence: flujo de caja libre descontado (millones de USD)
A3: Supuesto | B3: Valor | C3: Comentario
A4: Ventas 2025 | B4: ='Múltiplos (preliminar)'!B4 -> 50 | C4: Base
A5: Margen EBITDA normalizado | B5: 0.14 | C5: 15% reportado − 1 punto por costos laborales sindicales
A6: Capital de trabajo neto / ventas | B6: 0.12 | C6: Supuesto
A7: Tasa de ISR | B7: ='Costo de capital'!B10 -> 0.3
A8: Costo de capital (WACC) | B8: ='Costo de capital'!B14 -> 0.10975 | C8: Hoja Costo de capital
A9: Crecimiento a perpetuidad | B9: 0.04 | C9: Menor al 15% del mercado: crecimiento maduro
A10: Deuda bancaria detectada en la due diligence | B10: 15 | C10: Dato del caso
A11: Pago único por contingencias laborales (2026) | B11: 1 | C11: Revisión de contratos sindicales
A14: Concepto | B14: 2025 (base) | C14: 2026 | D14: 2027 | E14: 2028 | F14: 2029 | G14: 2030
A15: Crecimiento de ventas | C15: 0.12 | D15: 0.11 | E15: 0.1 | F15: 0.09 | G15: 0.08
A16: Ventas | B16: =B4 -> 50 | C16: =B16*(1+C15) -> 56 | D16: =C16*(1+D15) -> 62.16 | E16: =D16*(1+E15) -> 68.376 | F16: =E16*(1+F15) -> 74.52984 | G16: =F16*(1+G15) -> 80.492227
A17: EBITDA normalizado | C17: =C16*$B$5 -> 7.84 | D17: =D16*$B$5 -> 8.7024 | E17: =E16*$B$5 -> 9.57264 | F17: =F16*$B$5 -> 10.434178 | G17: =G16*$B$5 -> 11.268912
A18: (−) Depreciación y amortización | C18: 1.5 | D18: 1.6 | E18: 1.7 | F18: 1.8 | G18: 1.9
A19: (−) Contingencias laborales | C19: =$B$11 -> 1 | D19: 0 | E19: 0 | F19: 0 | G19: 0
A20: (=) EBIT | C20: =C17-C18-C19 -> 5.34 | D20: =D17-D18-D19 -> 7.1024 | E20: =E17-E18-E19 -> 7.87264 | F20: =F17-F18-F19 -> 8.6341776 | G20: =G17-G18-G19 -> 9.3689118
A21: (−) ISR | C21: =MAX(0,C20)*$B$7 -> 1.602 | D21: =MAX(0,D20)*$B$7 -> 2.13072 | E21: =MAX(0,E20)*$B$7 -> 2.361792 | F21: =MAX(0,F20)*$B$7 -> 2.5902533 | G21: =MAX(0,G20)*$B$7 -> 2.8106735
A22: (=) NOPAT | C22: =C20-C21 -> 3.738 | D22: =D20-D21 -> 4.97168 | E22: =E20-E21 -> 5.510848 | F22: =F20-F21 -> 6.0439243 | G22: =G20-G21 -> 6.5582383
A23: (+) Depreciación y amortización | C23: =C18 -> 1.5 | D23: =D18 -> 1.6 | E23: =E18 -> 1.7 | F23: =F18 -> 1.8 | G23: =G18 -> 1.9
A24: (−) Inversión en activos (capex) | C24: 2 | D24: 2.1 | E24: 2.2 | F24: 2.3 | G24: 2.3
A25: Capital de trabajo neto (saldo) | B25: =B16*$B$6 -> 6 | C25: =C16*$B$6 -> 6.72 | D25: =D16*$B$6 -> 7.4592 | E25: =E16*$B$6 -> 8.20512 | F25: =F16*$B$6 -> 8.9435808 | G25: =G16*$B$6 -> 9.6590673
A26: (−) Incremento en capital de trabajo | C26: =C25-B25 -> 0.72 | D26: =D25-C25 -> 0.7392 | E26: =E25-D25 -> 0.74592 | F26: =F25-E25 -> 0.7384608 | G26: =G25-F25 -> 0.71548646
A27: (=) Flujo de caja libre | C27: =C22+C23-C24-C26 -> 2.518 | D27: =D22+D23-D24-D26 -> 3.73248 | E27: =E22+E23-E24-E26 -> 4.264928 | F27: =F22+F23-F24-F26 -> 4.8054635 | G27: =G22+G23-G24-G26 -> 5.4427518
A29: Valor terminal en 2030 = FCL 2031 / (WACC − g) | G29: =G27*(1+B9)/(B8-B9) -> 81.153575
A30: Factor de descuento | C30: =1/(1+$B$8)^1 -> 0.90110385 | D30: =1/(1+$B$8)^2 -> 0.81198815 | E30: =1/(1+$B$8)^3 -> 0.73168565 | F30: =1/(1+$B$8)^4 -> 0.65932476 | G30: =1/(1+$B$8)^5 -> 0.59412008
A31: Valor presente del flujo (y del valor terminal) | C31: =(C27)*C30 -> 2.2689795 | D31: =(D27)*D30 -> 3.0307295 | E31: =(E27)*E30 -> 3.1205866 | F31: =(F27)*F30 -> 3.1683611 | G31: =(G27+G29)*G30 -> 51.448617
A33: Valor de la empresa (EV) | B33: =SUM(C31:G31) -> 63.037274
A34: (−) Deuda bancaria | B34: =B10 -> 15
A35: (=) Valor del capital = precio ajustado | B35: =B33-B34 -> 48.037274
A36: EV / EBITDA normalizado 2025 | B36: =B33/(B4*B5) -> 9.0053248
A38: Cifras en azul = supuestos; en negro = fórmulas. Paréntesis = cifras negativas.

Sheet Precio en 3 momentos
A1: Ajustes al precio de la transacción en los tres momentos clave (millones de USD)
A3: Momento | B3: Concepto | C3: Ajuste | D3: Precio | E3: Método o mecanismo
A4: 1. Antes de la auditoría | B4: Valor preliminar | D4: ='Múltiplos (preliminar)'!B8 -> 60 | E4: Múltiplos: 7.5 × 8.0x
A5: 2. Después de la due diligence | B5: Diferencia entre DCF y múltiplos | C5: ='Flujo de caja libre (DCF)'!B33-D4 -> 3.0372736 | E5: Flujo de caja libre con margen normalizado
B6: Valor de la empresa por DCF | D6: ='Flujo de caja libre (DCF)'!B33 -> 63.037274 | E6: WACC por CAPM
B7: (−) Deuda bancaria | C7: =-'Flujo de caja libre (DCF)'!B34 -> -15 | E7: Dato de la due diligence
B8: Precio ajustado | D8: =D6+C7 -> 48.037274 | E8: Coincide con el caso: USD 48 M
A9: 3. Al cierre | B9: (−) Cláusula: caída del capital de trabajo neto > 5% en 6 meses | C9: -3 | E9: Ajuste contractual (dato del caso)
B10: Precio mínimo si se activa la cláusula | D10: =D8+C9 -> 45.037274
A12: Reducción total frente al valor preliminar | D12: =D10-D4 -> -14.962726 | E12: =D12/D4 -> -0.24937877
A13: Capital de trabajo neto 2025 | D13: ='Flujo de caja libre (DCF)'!B25 -> 6
A14: Caída de 5% que activa la cláusula | D14: =D13*0.05 -> 0.3
A16: La cláusula descuenta USD 3 M aunque la caída mínima que la activa sea de unos USD 0.3 M: es una protección fuerte para el comprador.

Sheet Sinergias
A1: Sinergias estimadas para NutriTreats y valor creado con cada precio (millones de USD)
A3: Supuesto | B3: Valor | C3: Comentario
A4: Ahorro en compras de insumos (año completo) | B4: 1 | C4: ≈3.6% del costo de ventas de SweetKids (55% de USD 50 M)
A5: Ventas adicionales de NutriTreats en canales de SweetKids (año 3) | B5: 5 | C5: Barras y galletas en escuelas y tiendas de conveniencia
A6: Margen EBITDA sobre esas ventas | B6: ='Flujo de caja libre (DCF)'!B5 -> 0.14
A7: Inversión en planta que NutriTreats evita | B7: 20 | C7: Supuesto: costo de construir capacidad propia en México
A10: Concepto | B10: 2026 | C10: 2027 | D10: 2028 | E10: 2029 | F10: 2030
A11: Grado de captura | B11: 0.3 | C11: 0.7 | D11: 1 | E11: 1 | F11: 1
A12: Sinergias antes de impuestos | B12: =($B$4+$B$5*$B$6)*B11*(1+'Flujo de caja libre (DCF)'!$B$9)^0 -> 0.51 | C12: =($B$4+$B$5*$B$6)*C11*(1+'Flujo de caja libre (DCF)'!$B$9)^1 -> 1.2376 | D12: =($B$4+$B$5*$B$6)*D11*(1+'Flujo de caja libre (DCF)'!$B$9)^2 -> 1.83872 | E12: =($B$4+$B$5*$B$6)*E11*(1+'Flujo de caja libre (DCF)'!$B$9)^3 -> 1.9122688 | F12: =($B$4+$B$5*$B$6)*F11*(1+'Flujo de caja libre (DCF)'!$B$9)^4 -> 1.9887596
A13: Sinergias después de impuestos | B13: =B12*(1-'Flujo de caja libre (DCF)'!$B$7) -> 0.357 | C13: =C12*(1-'Flujo de caja libre (DCF)'!$B$7) -> 0.86632 | D13: =D12*(1-'Flujo de caja libre (DCF)'!$B$7) -> 1.287104 | E13: =E12*(1-'Flujo de caja libre (DCF)'!$B$7) -> 1.3385882 | F13: =F12*(1-'Flujo de caja libre (DCF)'!$B$7) -> 1.3921317
A14: Valor presente | B14: =(B13)/(1+'Flujo de caja libre (DCF)'!$B$8)^1 -> 0.32169408 | C14: =(C13)/(1+'Flujo de caja libre (DCF)'!$B$8)^2 -> 0.70344158 | D14: =(D13)/(1+'Flujo de caja libre (DCF)'!$B$8)^3 -> 0.94175553 | E14: =(E13)/(1+'Flujo de caja libre (DCF)'!$B$8)^4 -> 0.88256432 | F14: =(F13+F13*(1+'Flujo de caja libre (DCF)'!$B$9)/('Flujo de caja libre (DCF)'!$B$8-'Flujo de caja libre (DCF)'!$B$9))/(1+'Flujo de caja libre (DCF)'!$B$8)^5 -> 13.159382
A16: Valor presente de las sinergias | B16: =SUM(B14:F14) -> 16.008837
A18: Valor creado para NutriTreats | B18: Pagando USD 48 M | C18: Pagando USD 45 M
A19: Valor del capital de SweetKids (DCF) | B19: ='Flujo de caja libre (DCF)'!B35 -> 48.037274 | C19: ='Flujo de caja libre (DCF)'!B35 -> 48.037274
A20: (+) Valor presente de las sinergias | B20: =B16 -> 16.008837 | C20: =B16 -> 16.008837
A21: (−) Precio pagado | B21: ='Precio en 3 momentos'!D8 -> 48.037274 | C21: ='Precio en 3 momentos'!D10 -> 45.037274
A22: (=) Valor presente neto para NutriTreats | B22: =B19+B20-B21 -> 16.008837 | C22: =C19+C20-C21 -> 19.008837
A24: Cifras en azul = supuestos; en negro = fórmulas. La inversión evitada en planta no se suma al VPN; se usa como argumento estratégico.
